sorted/__init__.py
sorted/sorted.cpython-311-x86_64-linux-gnu.so
sorted_out-0.1.0.dist-info/METADATA
sorted_out-0.1.0.dist-info/WHEEL
sorted_out-0.1.0.dist-info/RECORD
