Metadata-Version: 2.4
Name: sorted-out
Version: 0.1.0
Summary: My Rust + Python package
Author-email: Your Name <you@example.com>
License: MIT
Requires-Python: >=3.10
